fastapi_advanced_filters/__init__.py
fastapi_advanced_filters/data_classes/__init__.py
fastapi_advanced_filters/data_classes/advanced_qsearch.py
fastapi_advanced_filters/data_classes/field_criteria.py
fastapi_advanced_filters/data_classes/filter_result.py
fastapi_advanced_filters/data_classes/pagination.py
fastapi_advanced_filters/data_classes/qsearch.py
fastapi_advanced_filters/data_classes/selectable.py
fastapi_advanced_filters/data_classes/sortby.py
fastapi_advanced_filters/enums.py
fastapi_advanced_filters/filter_metaclass/__init__.py
fastapi_advanced_filters/filter_metaclass/helpers/__init__.py
fastapi_advanced_filters/filter_metaclass/helpers/field_criteria.py
fastapi_advanced_filters/filter_metaclass/helpers/pagination.py
fastapi_advanced_filters/filter_metaclass/helpers/q_search.py
fastapi_advanced_filters/filter_metaclass/helpers/selectable.py
fastapi_advanced_filters/filter_metaclass/helpers/sortable.py
fastapi_advanced_filters/filter_metaclass/metaclass.py
fastapi_advanced_filters/filters/__init__.py
fastapi_advanced_filters/filters/base.py
fastapi_advanced_filters/filters/mixins/__init__.py
fastapi_advanced_filters/filters/mixins/filter.py
fastapi_advanced_filters/filters/mixins/pagination.py
fastapi_advanced_filters/filters/mixins/q_search.py
fastapi_advanced_filters/filters/mixins/selecting.py
fastapi_advanced_filters/filters/mixins/sorting.py
fastapi_advanced_filters/operation_mapping/__init__.py
fastapi_advanced_filters/operation_mapping/sqlalchemy_mapping.py
fastapi_advanced_filters/utils.py
fastapi_advanced_filters-0.1.0.dist-info/METADATA
fastapi_advanced_filters-0.1.0.dist-info/WHEEL
fastapi_advanced_filters-0.1.0.dist-info/RECORD
