Metadata-Version: 2.4
Name: fastapi_advanced_filters
Version: 0.1.0
Summary: A filter library for FastAPI with SQLAlchemy support.
License: MIT
Author: er5bus
Author-email: er5bus@example.com
Requires-Python: >=3.9,<4.0
Classifier: Framework :: FastAPI
Classifier: License :: OSI Approved :: MIT License
Classifier: Natural Language :: English
Classifier: Operating System :: OS Independent
Classifier: Programming Language :: Python
Classifier: Programming Language :: Python :: 3
Classifier: Programming Language :: Python :: 3.9
Classifier: Programming Language :: Python :: 3.10
Classifier: Programming Language :: Python :: 3.11
Classifier: Programming Language :: Python :: 3.12
Classifier: Programming Language :: Python :: 3.13
Classifier: Programming Language :: Python :: 3.14
Classifier: Programming Language :: Python :: 3 :: Only
Provides-Extra: all
Provides-Extra: sqlalchemy
Requires-Dist: SQLAlchemy (>=1.4.36,<2.1.0) ; extra == "sqlalchemy" or extra == "all"
Requires-Dist: fastapi (>=0.100.0,<1.0)
Requires-Dist: pydantic[email] (>=2.7.4,<3.0.0)
Project-URL: Homepage, https://github.com/py-library/fastapi_advanced_filters
Project-URL: Repository, https://github.com/py-library/fastapi_advanced_filters
